lobby/__init__.py
lobby/client.py
lobby_python-1.0.0.dist-info/LICENCE
lobby_python-1.0.0.dist-info/METADATA
lobby_python-1.0.0.dist-info/WHEEL
lobby_python-1.0.0.dist-info/top_level.txt
lobby_python-1.0.0.dist-info/RECORD
