Metadata-Version: 2.1
Name: lobby-python
Version: 1.0.0
Summary: Client for service discovery tool Lobby
Home-page: https://github.com/by-cx/lobby-python
Author: Adam Štrauch
Author-email: cx@initd.cz
License: UNKNOWN
Project-URL: Bug Tracker, https://github.com/by-cx/lobby-python/issues
Platform: UNKNOWN
Classifier: Programming Language :: Python :: 3
Classifier: License :: OSI Approved :: BSD License
Classifier: Operating System :: OS Independent
Classifier: Development Status :: 5 - Production/Stable
Classifier: Natural Language :: English
Classifier: Topic :: Software Development :: Libraries :: Python Modules
Requires-Python: >=3.5
License-File: LICENCE
